barch/__init__.py
barch/fingerprint.py
barch-0.1.0.dist-info/WHEEL
barch-0.1.0.dist-info/METADATA
barch-0.1.0.dist-info/RECORD
