Metadata-Version: 2.1
Name: barch
Version: 0.1.0
Summary: Tool to support backup and archival
Author: Joachim Hereth
Author-email: qudade-barch@quda.de
Requires-Python: >=3.7,<4.0
Classifier: Programming Language :: Python :: 3
Classifier: Programming Language :: Python :: 3.7
Requires-Dist: click (>=7.0)
Requires-Dist: xxhash (>=1.3,<2.0)
